[{"class_name": "contrast", "bbox": "622 297 1336 1062", "used": true}, {"class_name": "contrast", "bbox": "358 10 539 267", "used": true}, {"class_name": "saturation", "bbox": "13 8 243 781", "used": true}, {"class_name": "saturation", "bbox": "48 753 472 1056", "used": false}, {"class_name": "specularity", "bbox": "105 649 188 790", "used": true}, {"class_name": "specularity", "bbox": "201 715 249 782", "used": true}, {"class_name": "specularity", "bbox": "75 786 121 833", "used": true}, {"class_name": "specularity", "bbox": "133 809 271 911", "used": false}, {"class_name": "specularity", "bbox": "199 894 221 923", "used": false}, {"class_name": "specularity", "bbox": "230 945 266 984", "used": true}, {"class_name": "specularity", "bbox": "96 877 162 984", "used": false}, {"class_name": "specularity", "bbox": "161 962 199 1016", "used": true}, {"class_name": "specularity", "bbox": "165 1001 210 1045", "used": false}, {"class_name": "bubbles", "bbox": "325 894 351 927", "used": false}, {"class_name": "specularity", "bbox": "1049 360 1081 412", "used": true}, {"class_name": "specularity", "bbox": "920 328 949 367", "used": true}, {"class_name": "specularity", "bbox": "558 38 591 91", "used": true}, {"class_name": "specularity", "bbox": "413 119 454 153", "used": true}, {"class_name": "bubbles", "bbox": "537 327 600 366", "used": false}, {"class_name": "specularity", "bbox": "522 257 571 340", "used": false}, {"class_name": "specularity", "bbox": "631 423 689 478", "used": true}, {"class_name": "specularity", "bbox": "583 541 609 576", "used": false}, {"class_name": "specularity", "bbox": "925 73 962 102", "used": false}, {"class_name": "contrast", "bbox": "672 11 1328 349", "used": false}, {"class_name": "contrast", "bbox": "495 474 546 613", "used": false}, {"class_name": "contrast", "bbox": "541 690 657 862", "used": false}]