[{"class_name": "artifact", "bbox": "160 193 253 293", "used": false}, {"class_name": "artifact", "bbox": "357 352 464 439", "used": false}, {"class_name": "artifact", "bbox": "121 414 252 534", "used": false}, {"class_name": "contrast", "bbox": "240 2 999 571", "used": true}, {"class_name": "saturation", "bbox": "900 414 961 541", "used": false}, {"class_name": "saturation", "bbox": "848 515 914 561", "used": false}, {"class_name": "saturation", "bbox": "875 570 1026 794", "used": true}, {"class_name": "saturation", "bbox": "1000 647 1096 736", "used": false}, {"class_name": "bubbles", "bbox": "988 757 1021 790", "used": false}, {"class_name": "bubbles", "bbox": "924 864 956 911", "used": false}, {"class_name": "specularity", "bbox": "743 969 804 1019", "used": false}, {"class_name": "specularity", "bbox": "754 103 771 127", "used": false}, {"class_name": "specularity", "bbox": "779 110 829 168", "used": true}, {"class_name": "specularity", "bbox": "639 5 667 31", "used": true}, {"class_name": "specularity", "bbox": "779 17 877 117", "used": false}, {"class_name": "specularity", "bbox": "642 76 693 118", "used": true}, {"class_name": "specularity", "bbox": "700 10 750 40", "used": false}, {"class_name": "specularity", "bbox": "581 300 617 335", "used": false}, {"class_name": "bubbles", "bbox": "458 293 542 420", "used": true}, {"class_name": "blur", "bbox": "245 495 457 865", "used": false}]