[{"class_name": "bubbles", "bbox": "381 105 511 190", "used": true}, {"class_name": "bubbles", "bbox": "306 390 382 504", "used": true}, {"class_name": "bubbles", "bbox": "96 321 190 413", "used": true}, {"class_name": "bubbles", "bbox": "353 348 396 381", "used": true}, {"class_name": "bubbles", "bbox": "339 317 382 346", "used": false}, {"class_name": "artifact", "bbox": "19 408 53 472", "used": false}, {"class_name": "saturation", "bbox": "309 463 383 508", "used": true}, {"class_name": "contrast", "bbox": "120 97 418 294", "used": true}]