[{"class_name": "bubbles", "bbox": "284 42 391 142", "used": false}, {"class_name": "bubbles", "bbox": "312 341 359 424", "used": false}, {"class_name": "bubbles", "bbox": "101 76 224 155", "used": false}, {"class_name": "bubbles", "bbox": "104 39 446 257", "used": false}, {"class_name": "bubbles", "bbox": "152 266 181 300", "used": false}, {"class_name": "bubbles", "bbox": "128 318 154 344", "used": false}, {"class_name": "bubbles", "bbox": "100 293 127 350", "used": false}, {"class_name": "bubbles", "bbox": "93 413 159 478", "used": false}, {"class_name": "bubbles", "bbox": "318 434 367 506", "used": false}, {"class_name": "bubbles", "bbox": "406 304 436 349", "used": false}, {"class_name": "bubbles", "bbox": "378 340 413 392", "used": false}, {"class_name": "artifact", "bbox": "5 112 24 245", "used": false}, {"class_name": "artifact", "bbox": "47 2 89 63", "used": false}, {"class_name": "artifact", "bbox": "24 342 50 413", "used": false}, {"class_name": "specularity", "bbox": "197 388 254 456", "used": true}, {"class_name": "specularity", "bbox": "468 153 484 178", "used": false}, {"class_name": "specularity", "bbox": "482 184 509 247", "used": true}, {"class_name": "specularity", "bbox": "488 381 506 410", "used": true}, {"class_name": "specularity", "bbox": "400 461 438 495", "used": true}, {"class_name": "specularity", "bbox": "384 417 411 441", "used": false}, {"class_name": "specularity", "bbox": "374 451 390 491", "used": false}, {"class_name": "specularity", "bbox": "451 91 470 129", "used": true}, {"class_name": "bubbles", "bbox": "235 260 259 284", "used": false}, {"class_name": "bubbles", "bbox": "244 333 262 354", "used": false}, {"class_name": "bubbles", "bbox": "274 335 293 363", "used": false}, {"class_name": "bubbles", "bbox": "171 349 193 373", "used": false}, {"class_name": "bubbles", "bbox": "200 465 220 488", "used": false}, {"class_name": "specularity", "bbox": "35 439 57 473", "used": false}, {"class_name": "artifact", "bbox": "74 72 101 105", "used": false}, {"class_name": "artifact", "bbox": "40 79 67 123", "used": false}, {"class_name": "artifact", "bbox": "94 0 121 24", "used": false}, {"class_name": "bubbles", "bbox": "419 3 495 68", "used": false}, {"class_name": "bubbles", "bbox": "342 4 394 29", "used": false}, {"class_name": "bubbles", "bbox": "124 1 166 27", "used": false}, {"class_name": "bubbles", "bbox": "475 245 505 317", "used": false}, {"class_name": "bubbles", "bbox": "484 314 507 372", "used": false}]