[{"class_name": "specularity", "bbox": "279 445 337 497", "used": true}, {"class_name": "specularity", "bbox": "338 173 417 258", "used": true}, {"class_name": "specularity", "bbox": "72 279 102 308", "used": false}, {"class_name": "specularity", "bbox": "30 357 58 386", "used": false}, {"class_name": "specularity", "bbox": "163 387 203 417", "used": true}, {"class_name": "specularity", "bbox": "240 477 277 494", "used": true}, {"class_name": "artifact", "bbox": "160 208 216 248", "used": true}, {"class_name": "artifact", "bbox": "406 137 446 164", "used": true}, {"class_name": "artifact", "bbox": "329 18 411 69", "used": true}, {"class_name": "artifact", "bbox": "263 288 340 346", "used": false}, {"class_name": "artifact", "bbox": "171 263 244 290", "used": false}, {"class_name": "artifact", "bbox": "46 427 69 448", "used": false}, {"class_name": "instrument", "bbox": "145 387 393 506", "used": true}, {"class_name": "contrast", "bbox": "295 316 506 498", "used": false}]