[{"class_name": "artifact", "bbox": "136 126 213 234", "used": false}, {"class_name": "artifact", "bbox": "451 130 498 204", "used": true}, {"class_name": "artifact", "bbox": "443 30 489 61", "used": true}, {"class_name": "artifact", "bbox": "398 91 414 114", "used": false}, {"class_name": "artifact", "bbox": "386 139 409 166", "used": false}, {"class_name": "artifact", "bbox": "316 160 346 204", "used": true}, {"class_name": "artifact", "bbox": "369 277 394 319", "used": true}, {"class_name": "artifact", "bbox": "320 451 369 504", "used": true}, {"class_name": "artifact", "bbox": "445 395 491 450", "used": true}, {"class_name": "artifact", "bbox": "452 295 483 332", "used": true}, {"class_name": "artifact", "bbox": "469 235 489 263", "used": false}, {"class_name": "bubbles", "bbox": "146 264 173 306", "used": true}, {"class_name": "contrast", "bbox": "13 2 238 181", "used": true}]