[{"class_name": "artifact", "bbox": "75 62 120 129", "used": true}, {"class_name": "artifact", "bbox": "143 77 206 125", "used": true}, {"class_name": "artifact", "bbox": "258 2 303 15", "used": true}, {"class_name": "artifact", "bbox": "378 4 412 17", "used": true}, {"class_name": "artifact", "bbox": "477 48 509 109", "used": true}, {"class_name": "artifact", "bbox": "458 106 489 156", "used": false}, {"class_name": "artifact", "bbox": "457 256 509 393", "used": true}, {"class_name": "artifact", "bbox": "2 171 30 236", "used": true}, {"class_name": "artifact", "bbox": "54 133 77 173", "used": true}, {"class_name": "contrast", "bbox": "54 304 304 507", "used": true}, {"class_name": "instrument", "bbox": "41 359 343 506", "used": false}]