[{"class_name": "artifact", "bbox": "399 51 486 203", "used": true}, {"class_name": "artifact", "bbox": "498 96 612 215", "used": false}, {"class_name": "artifact", "bbox": "585 59 625 96", "used": false}, {"class_name": "artifact", "bbox": "614 90 713 192", "used": false}, {"class_name": "specularity", "bbox": "246 197 314 253", "used": true}, {"class_name": "specularity", "bbox": "299 357 344 393", "used": true}, {"class_name": "saturation", "bbox": "247 384 407 533", "used": true}, {"class_name": "contrast", "bbox": "428 58 722 528", "used": true}]